README.md
setup.py
data_tool/__init__.py
data_tool.egg-info/PKG-INFO
data_tool.egg-info/SOURCES.txt
data_tool.egg-info/dependency_links.txt
data_tool.egg-info/requires.txt
data_tool.egg-info/top_level.txt
data_tool/map/__init__.py
data_tool/map/main.py
data_tool/map/pos_coord.py
data_tool/map/round_plan.py
data_tool/map/test.py
data_tool/reptile/__init__.py
data_tool/reptile/trainticket.py
data_tool/rule_date/__init__.py
data_tool/rule_date/date_parser.py
data_tool/rule_date/dict.txt
data_tool/weather/__init__.py
data_tool/weather/normalization.py
data_tool/weather/weather.py