Metadata-Version: 1.0
Name: data-tool
Version: 0.0.17
Summary: data_tool
Home-page: https://github.com/shfshf/data_tool
Author: Hanfeng Song
Author-email: 1316478299@qq.com
License: Apache 2.0
Platform: UNKNOWN
